lazyvpn/__init__.py
lazyvpn/config.py
lazyvpn/errors.py
lazyvpn/main.py
lazyvpn/ui.py
lazyvpn2-0.0.30.data/scripts/lazyvpn
lazyvpn2-0.0.30.data/scripts/lazyvpn.cmd
lazyvpn2-0.0.30.dist-info/METADATA
lazyvpn2-0.0.30.dist-info/WHEEL
lazyvpn2-0.0.30.dist-info/top_level.txt
lazyvpn2-0.0.30.dist-info/RECORD
