Metadata-Version: 2.1
Name: lazyvpn2
Version: 0.0.30
Summary: A CLI to connect to vpn via cisco anyconnect in one step
Home-page: https://gitlab.zgtools.net/zillow/hackweek/lazyvpn
Author: Yuzhong Li, Clayton Blythe, Kareem Harouny 
Author-email: yuzhongl@zillowgroup.com, claytonb@zillowgroup.com, kareemharouny@gmail.com
License: Apache License, v2.0
Classifier: Natural Language :: English
Classifier: Programming Language :: Python :: 3 :: Only
Classifier: License :: OSI Approved :: Apache Software License
Requires-Dist: configparser <4.0.0,>=3.5.0
Requires-Dist: keyring >=10.4.0
